fluorescence_polarity/__init__.py
fluorescence_polarity/test_fp_functions.py
fluorescence_polarity/data_for_testing/fluor_polarity_txy_test.csv
fluorescence_polarity/data_for_testing/fluor_polarity_xy_test.csv
fluorescence_polarity/data_for_testing/test_DataFrame.csv
fluorescence_polarity/data_for_testing/test_images/fluor_0000.tif
fluorescence_polarity/data_for_testing/test_images/fluor_0001.tif
fluorescence_polarity/data_for_testing/test_images/fluor_0002.tif
fluorescence_polarity/data_for_testing/test_images/fluor_0003.tif
fluorescence_polarity/data_for_testing/test_images/fluor_0004.tif
fluorescence_polarity/data_for_testing/test_images/fluor_0005.tif
fluorescence_polarity/data_for_testing/test_images/fluor_0006.tif
fluorescence_polarity/data_for_testing/test_images/fluor_0007.tif
fluorescence_polarity/data_for_testing/test_images/fluor_0008.tif
fluorescence_polarity/data_for_testing/test_images/fluor_0009.tif
fluorescence_polarity/data_for_testing/test_images/fluor_0010.tif
fluorescence_polarity/data_for_testing/test_images/fluor_0011.tif
fluorescence_polarity/data_for_testing/test_images/fluor_0012.tif
fluorescence_polarity/data_for_testing/test_images/fluor_0013.tif
fluorescence_polarity/data_for_testing/test_images/fluor_0014.tif
fluorescence_polarity/data_for_testing/test_images/fluor_0015.tif
fluorescence_polarity/data_for_testing/test_images/fluor_0016.tif
fluorescence_polarity/data_for_testing/test_images/fluor_0017.tif
fluorescence_polarity/data_for_testing/test_images/fluor_0018.tif
fluorescence_polarity/data_for_testing/test_images/fluor_0019.tif
fluorescence_polarity/data_for_testing/test_images/fluor_0020.tif
fluorescence_polarity/data_for_testing/test_images/fluor_0021.tif
fluorescence_polarity/data_for_testing/test_images/fluor_0022.tif
fluorescence_polarity/data_for_testing/test_images/fluor_0023.tif
fluorescence_polarity/data_for_testing/test_images/fluor_0024.tif
fluorescence_polarity/data_for_testing/test_images/fluor_0025.tif
fluorescence_polarity-0.1.dist-info/LICENSE
fluorescence_polarity-0.1.dist-info/METADATA
fluorescence_polarity-0.1.dist-info/WHEEL
fluorescence_polarity-0.1.dist-info/top_level.txt
fluorescence_polarity-0.1.dist-info/RECORD
