Metadata-Version: 2.1
Name: fluorescence-polarity
Version: 0.1
Summary: Methods for quantifying spatial polarization of fluorescence markers
Home-page: https://github.com/bgraziano/fluorescence_polarity
Author: Brian Graziano
Author-email: brgrazian@gmail.com
License: MIT
Platform: UNKNOWN
Requires-Python: >=3.7
Requires-Dist: numpy (>=1.16.4)
Requires-Dist: mpu
Requires-Dist: scikit-image (>=0.15.0)
Requires-Dist: pandas (>=0.25.0)
Requires-Dist: scipy (>=1.3.0)
